migrate_sql/__init__.py
migrate_sql/apps.py
migrate_sql/autodetector.py
migrate_sql/config.py
migrate_sql/graph.py
migrate_sql/operations.py
django_migrate_sql_3-3.0.2.dist-info/LICENSE
django_migrate_sql_3-3.0.2.dist-info/METADATA
django_migrate_sql_3-3.0.2.dist-info/WHEEL
django_migrate_sql_3-3.0.2.dist-info/top_level.txt
django_migrate_sql_3-3.0.2.dist-info/RECORD
