Metadata-Version: 2.1
Name: django-migrate-sql-3
Version: 3.0.2
Summary: A package parsing the PostgreSQL connection service file
Author-email: Bogdan Klichuk <klichuk@github.com>, Festicket <festicket@github.com>, Denis Rouzaud <info@opengis.ch>
License: MIT License
Project-URL: homepage, https://github.com/opengisch/django-migrate-sql
Project-URL: repository, https://github.com/opengisch/django-migrate-sql
Project-URL: tracker, https://github.com/opengisch/django-migrate-sql/issues
Keywords: postgres,service
Classifier: Development Status :: 3 - Alpha
Classifier: Framework :: Django
Classifier: Intended Audience :: Developers
Classifier: License :: OSI Approved :: BSD License
Classifier: Natural Language :: English
Classifier: Framework :: Django :: 3.2
Classifier: Framework :: Django :: 4.2
Classifier: Framework :: Django :: 5.0
Requires-Python: >=3.9
License-File: LICENSE
